IoTNetworkMalwareClassifier/__init__.py
IoTNetworkMalwareClassifier/classifier.py
IoTNetworkMalwareClassifier/data/categorical_label_encoder_conn_state.pkl
IoTNetworkMalwareClassifier/data/categorical_label_encoder_history.pkl
IoTNetworkMalwareClassifier/data/categorical_label_encoder_proto.pkl
IoTNetworkMalwareClassifier/data/label_encoder.pkl
IoTNetworkMalwareClassifier/data/model.h5
IoTNetworkMalwareClassifier/data/standard_scaler.pkl
IoTNetworkMalwareClassifier/data/weights.h5
IoTNetworkMalwareClassifier-0.0.20.dist-info/LICENSE
IoTNetworkMalwareClassifier-0.0.20.dist-info/METADATA
IoTNetworkMalwareClassifier-0.0.20.dist-info/WHEEL
IoTNetworkMalwareClassifier-0.0.20.dist-info/top_level.txt
IoTNetworkMalwareClassifier-0.0.20.dist-info/RECORD
