Metadata-Version: 2.1
Name: IoTNetworkMalwareClassifier
Version: 0.0.20
Summary: 🛡️ The IoT Network Malware Classifier 🚀 is an advanced solution tackling security concerns in IoT, employing deep learning for precise malware detection in network traffic.
Home-page: https://github.com/sergio11/iot_network_malware_classifier
Author: Sergio Sánchez Sánchez
Author-email: dreamsoftware92@gmail.com
Keywords: IoT,malware,network traffic,Deep Learning,classification
Classifier: Development Status :: 4 - Beta
Classifier: Intended Audience :: Developers
Classifier: License :: OSI Approved :: MIT License
Classifier: Programming Language :: Python :: 3
Classifier: Programming Language :: Python :: 3.7
Classifier: Programming Language :: Python :: 3.8
Classifier: Programming Language :: Python :: 3.9
Classifier: Programming Language :: Python :: 3.10
Requires-Python: >=3.7, <4
License-File: LICENSE
Requires-Dist: scikit-learn ==1.4.2
Requires-Dist: numpy ==1.25.2
Requires-Dist: tensorflow ==2.15.0
Requires-Dist: ipaddress ==1.0.23
Requires-Dist: pandas ==2.2.2
